{
    "algorithm": "pso",
    "nodes": [
        {
            "rpcPort": 51790,
            "interface": "lo",
            "port": 37223,
            "id": 1,
            "address": "127.0.0.1"
        },
        {
            "rpcPort": 33666,
            "interface": "lo",
            "port": 46964,
            "id": 2,
            "address": "127.0.0.1"
        },
        {
            "rpcPort": 45181,
            "interface": "lo",
            "port": 39707,
            "id": 3,
            "address": "127.0.0.1"
        }
    ],
    "mode": "local",
    "testEndpoint": "127.0.0.1:40069"
}